{
  "run_id": "run_1769314606",
  "start_time": "2026-01-24T22:16:46.532931",
  "scenarios": [
    {
      "id": "TC001",
      "status": "passed",
      "steps": [
        {
          "id": "step_1",
          "status": "passed",
          "attempt": 1
        },
        {
          "id": "step_2",
          "status": "passed",
          "attempt": 1
        },
        {
          "id": "step_3",
          "status": "passed",
          "attempt": 1
        },
        {
          "id": "step_4",
          "status": "passed",
          "attempt": 1
        },
        {
          "id": "step_4_ai_1",
          "status": "passed",
          "attempt": 1
        },
        {
          "id": "step_4_ai_2",
          "status": "passed",
          "attempt": 1
        },
        {
          "id": "step_6",
          "status": "passed",
          "attempt": 1
        },
        {
          "id": "step_6_ai_1",
          "status": "passed",
          "attempt": 1
        },
        {
          "id": "step_7",
          "status": "passed",
          "attempt": 1
        },
        {
          "id": "step_7_ai_1",
          "status": "passed",
          "attempt": 2
        },
        {
          "id": "step_8",
          "status": "passed",
          "attempt": 1
        },
        {
          "id": "step_10",
          "status": "passed",
          "attempt": 1
        },
        {
          "id": "step_11",
          "status": "passed",
          "attempt": 1
        },
        {
          "id": "step_12",
          "status": "passed",
          "attempt": 1
        },
        {
          "id": "step_13",
          "status": "passed",
          "attempt": 1
        },
        {
          "id": "step_13_ai_1",
          "status": "passed",
          "attempt": 1
        },
        {
          "id": "step_14",
          "status": "passed",
          "attempt": 1
        },
        {
          "id": "step_15",
          "status": "passed",
          "attempt": 1
        },
        {
          "id": "step_15_ai_1",
          "status": "passed",
          "attempt": 1
        },
        {
          "id": "step_16",
          "status": "passed",
          "attempt": 1
        },
        {
          "id": "step_17",
          "status": "passed",
          "attempt": 2
        },
        {
          "id": "step_18",
          "status": "passed",
          "attempt": 1
        },
        {
          "id": "step_19",
          "status": "passed",
          "attempt": 1
        },
        {
          "id": "step_20",
          "status": "passed",
          "attempt": 1
        },
        {
          "id": "step_21",
          "status": "passed",
          "attempt": 2
        },
        {
          "id": "step_22",
          "status": "passed",
          "attempt": 1
        },
        {
          "id": "step_23",
          "status": "passed",
          "attempt": 1
        },
        {
          "id": "step_24",
          "status": "passed",
          "attempt": 1
        },
        {
          "id": "step_25",
          "status": "passed",
          "attempt": 1
        },
        {
          "id": "step_26",
          "status": "passed",
          "attempt": 1
        },
        {
          "id": "step_27",
          "status": "passed",
          "attempt": 1
        },
        {
          "id": "step_27_ai_1",
          "status": "passed",
          "attempt": 1
        }
      ]
    }
  ],
  "end_time": "2026-01-24T22:18:54.470912"
}